testforallen1/__init__.py
testforallen1/main.py
testforallen1-1.2.dist-info/METADATA
testforallen1-1.2.dist-info/WHEEL
testforallen1-1.2.dist-info/top_level.txt
testforallen1-1.2.dist-info/RECORD
