Metadata-Version: 2.1
Name: testforallen1
Version: 1.2
Summary: This is a test of the setup
Home-page: https://github/allensrj/
Author: allensrj
Author-email: allensrj@qq.com
License: MIT
